enkeksi/__init__.py
enkeksi/cli.py
enkeksi/mdprocess.py
enkeksi-0.3.0.dist-info/LICENSE
enkeksi-0.3.0.dist-info/METADATA
enkeksi-0.3.0.dist-info/WHEEL
enkeksi-0.3.0.dist-info/entry_points.txt
enkeksi-0.3.0.dist-info/top_level.txt
enkeksi-0.3.0.dist-info/RECORD
