Metadata-Version: 2.1
Name: enkeksi
Version: 0.3.0
Summary: enkeksi takes a markdown-formatted input and executes the sql queries found in it, and returns a pretty markdown-formatted output where the results of the SQL queries have been added. To make usage of package easy, enkeksi comes with a command line tool markdown-sql-eval which can be used to process markdown files. Project is developed and hosted in GitHub: https://github.com/ahojukka5/enkeksi.
Home-page: https://github.com/ahojukka5/enkeksi
Author: Jukka Aho
Author-email: ahojukka5@gmail.com
License: UNKNOWN
Keywords: markdown sql evaluator
Platform: UNKNOWN
Classifier: Programming Language :: Python :: 3
Classifier: License :: OSI Approved :: MIT License
Classifier: Operating System :: OS Independent
Provides-Extra: test
Requires-Dist: pytest ; extra == 'test'
Requires-Dist: pytest-cov ; extra == 'test'
Requires-Dist: pytest-pycodestyle ; extra == 'test'
Requires-Dist: pytest-pep8 ; extra == 'test'
Requires-Dist: pytest-flake8 ; extra == 'test'
